abbfreeathome/__init__.py
abbfreeathome/api.py
abbfreeathome/const.py
abbfreeathome/dev-requirements.txt
abbfreeathome/device.py
abbfreeathome/exceptions.py
abbfreeathome/floorplan.py
abbfreeathome/freeathome.py
abbfreeathome/bin/__init__.py
abbfreeathome/bin/function.py
abbfreeathome/bin/interface.py
abbfreeathome/bin/pairing.py
abbfreeathome/bin/parameter.py
abbfreeathome/channels/__init__.py
abbfreeathome/channels/air_quality_sensor.py
abbfreeathome/channels/base.py
abbfreeathome/channels/blind_sensor.py
abbfreeathome/channels/brightness_sensor.py
abbfreeathome/channels/carbon_monoxide_sensor.py
abbfreeathome/channels/cover_actuator.py
abbfreeathome/channels/des_door_opener_actuator.py
abbfreeathome/channels/des_door_ringing_sensor.py
abbfreeathome/channels/dimming_actuator.py
abbfreeathome/channels/force_on_off_sensor.py
abbfreeathome/channels/heating_actuator.py
abbfreeathome/channels/movement_detector.py
abbfreeathome/channels/rain_sensor.py
abbfreeathome/channels/room_temperature_controller.py
abbfreeathome/channels/smoke_detector.py
abbfreeathome/channels/switch_actuator.py
abbfreeathome/channels/switch_sensor.py
abbfreeathome/channels/temperature_sensor.py
abbfreeathome/channels/trigger.py
abbfreeathome/channels/valve_actuator.py
abbfreeathome/channels/wind_sensor.py
abbfreeathome/channels/window_door_sensor.py
abbfreeathome/channels/virtual/__init__.py
abbfreeathome/channels/virtual/virtual_brightness_sensor.py
abbfreeathome/channels/virtual/virtual_energy_battery.py
abbfreeathome/channels/virtual/virtual_energy_inverter.py
abbfreeathome/channels/virtual/virtual_energy_two_way_meter.py
abbfreeathome/channels/virtual/virtual_rain_sensor.py
abbfreeathome/channels/virtual/virtual_room_temperature_controller.py
abbfreeathome/channels/virtual/virtual_switch_actuator.py
abbfreeathome/channels/virtual/virtual_temperature_sensor.py
abbfreeathome/channels/virtual/virtual_wind_sensor.py
abbfreeathome/channels/virtual/virtual_window_door_sensor.py
local_abbfreeathome-3.4.0.dist-info/METADATA
local_abbfreeathome-3.4.0.dist-info/WHEEL
local_abbfreeathome-3.4.0.dist-info/licenses/LICENSE
local_abbfreeathome-3.4.0.dist-info/RECORD
