Metadata-Version: 2.4
Name: local-abbfreeathome
Version: 3.4.0
Summary: A python package designed to interact with the ABB (Busch Jaeger) Free@Home System over the Local API
Project-URL: Homepage, https://github.com/kingsleyadam/local-abbfreeathome
Project-URL: Issues, https://github.com/kingsleyadam/local-abbfreeathome/issues
Author-email: Adam Kingsley <adam@kingsley.io>
License-File: LICENSE
Classifier: License :: OSI Approved :: MIT License
Classifier: Operating System :: OS Independent
Classifier: Programming Language :: Python :: 3
Requires-Python: >=3.12
Requires-Dist: aiohttp
Requires-Dist: backoff
Requires-Dist: packaging
